pgmpy_rcr/__init__.py
pgmpy_rcr/global_vars.py
pgmpy_rcr-0.1.6.dist-info/licenses/LICENSE
pgmpy_rcr-0.1.6.dist-info/METADATA
pgmpy_rcr-0.1.6.dist-info/WHEEL
pgmpy_rcr-0.1.6.dist-info/top_level.txt
pgmpy_rcr-0.1.6.dist-info/RECORD
