Metadata-Version: 2.4
Name: pgmpy-rcr
Version: 0.1.6
Summary: A customized fork of pgmpy for RCR library compatibility
Author-email: Ankur Ankan <ankurankan@gmail.com>, Valentin Lacombe <lacombevalentin@outlook.fr>
License: The MIT License (MIT)
Project-URL: Documentation, https://www.pgmpy.org
Project-URL: Download, https://pypi.org/project/pgmpy/#files
Project-URL: Homepage, https://www.pgmpy.org
Project-URL: Repository, https://github.com/pgmpy/pgmpy
Classifier: Programming Language :: Python :: 3.10
Classifier: Programming Language :: Python :: 3.11
Classifier: Programming Language :: Python :: 3.12
Classifier: Programming Language :: Python :: 3.13
Classifier: Intended Audience :: Education
Classifier: Intended Audience :: Science/Research
Classifier: Operating System :: Unix
Classifier: Operating System :: Microsoft :: Windows
Classifier: Operating System :: MacOS
Classifier: Topic :: Scientific/Engineering
Classifier: Topic :: Scientific/Engineering :: Artificial Intelligence
Classifier: Topic :: Scientific/Engineering :: Bio-Informatics
Requires-Python: <3.14,>=3.10
License-File: LICENSE
Requires-Dist: networkx>=3.0
Requires-Dist: numpy>=2.0
Requires-Dist: scipy>=1.10
Requires-Dist: scikit-learn>=1.2
Requires-Dist: pandas>=1.5
Requires-Dist: statsmodels>=0.14.5
Requires-Dist: tqdm>=4.64
Requires-Dist: pyparsing>=3.0
Requires-Dist: joblib>=1.2
Requires-Dist: opt_einsum>=3.3
Requires-Dist: scikit-base>=0.12.4
Requires-Dist: matplotlib>=3.10.7
Requires-Dist: pygraphviz
Requires-Dist: daft-pgm>=0.1.4
Provides-Extra: torch
Requires-Dist: torch>=2.5; extra == "torch"
Requires-Dist: pyro-ppl>=1.9.1; extra == "torch"
Provides-Extra: optional
Requires-Dist: daft-pgm>=0.1.4; extra == "optional"
Requires-Dist: xgboost>=2.0.3; extra == "optional"
Requires-Dist: litellm==1.61.15; extra == "optional"
Requires-Dist: pyparsing>=3.0; extra == "optional"
Requires-Dist: pygraphviz; extra == "optional"
Requires-Dist: torch>=2.5; extra == "optional"
Requires-Dist: pyro-ppl>=1.9.1; extra == "optional"
Provides-Extra: tests
Requires-Dist: xdoctest>=0.11.0; extra == "tests"
Requires-Dist: pytest>=3.3.1; extra == "tests"
Requires-Dist: pytest-cov; extra == "tests"
Requires-Dist: pytest-xdist; extra == "tests"
Requires-Dist: coverage>=4.3.4; extra == "tests"
Requires-Dist: mock; extra == "tests"
Requires-Dist: black; extra == "tests"
Requires-Dist: pre-commit; extra == "tests"
Provides-Extra: docs
Requires-Dist: sphinx>=5.0; extra == "docs"
Requires-Dist: nbsphinx; extra == "docs"
Requires-Dist: numpydoc; extra == "docs"
Requires-Dist: sphinx_rtd_theme; extra == "docs"
Requires-Dist: sphinx-copybutton; extra == "docs"
Requires-Dist: sphinx-design; extra == "docs"
Requires-Dist: sphinxext-opengraph; extra == "docs"
Provides-Extra: all
Requires-Dist: networkx>=3.0; extra == "all"
Requires-Dist: numpy>=2.0; extra == "all"
Requires-Dist: scipy>=1.10; extra == "all"
Requires-Dist: scikit-learn>=1.2; extra == "all"
Requires-Dist: pandas>=1.5; extra == "all"
Requires-Dist: torch>=2.5; extra == "all"
Requires-Dist: statsmodels>=0.13; extra == "all"
Requires-Dist: tqdm>=4.64; extra == "all"
Requires-Dist: joblib>=1.2; extra == "all"
Requires-Dist: opt_einsum>=3.3; extra == "all"
Requires-Dist: pyro-ppl>=1.9.1; extra == "all"
Requires-Dist: daft-pgm>=0.1.4; extra == "all"
Requires-Dist: xgboost>=2.0.3; extra == "all"
Requires-Dist: litellm==1.61.15; extra == "all"
Requires-Dist: pyparsing>=3.0; extra == "all"
Dynamic: license-file
